[{"max_percent": 98, "Match?": true}, {"max_percent": 98, "Match?": true}, {"max_percent": 100, "Match?": true}, {"max_percent": 100, "Match?": true}, {"max_percent": 96, "Match?": true}, {"max_percent": 98, "Match?": true}, {"max_percent": 100, "Match?": false}, {"max_percent": 83, "Match?": true}, {"max_percent": 83, "Match?": true}, {"max_percent": 100, "Match?": true}, {"max_percent": 73, "Match?": false}, {"max_percent": 100, "Match?": true}, {"max_percent": 99, "Match?": false}, {"max_percent": 1, "Match?": false}, {"max_percent": 92, "Match?": true}, {"max_percent": 100, "Match?": true}, {"max_percent": 96, "Match?": true}, {"max_percent": 89, "Match?": false}, {"max_percent": 70, "Match?": true}, {"max_percent": 44, "Match?": true}, {"max_percent": 100, "Match?": true}, {"max_percent": 96, "Match?": true}, {"max_percent": 61, "Match?": false}, {"max_percent": 100, "Match?": true}, {"max_percent": 93, "Match?": true}, {"max_percent": 93, "Match?": true}, {"max_percent": 100, "Match?": false}, {"max_percent": 92, "Match?": true}, {"max_percent": 100, "Match?": true}, {"max_percent": 100, "Match?": true}, {"max_percent": 98, "Match?": false}, {"max_percent": 79, "Match?": false}, {"max_percent": 57, "Match?": true}, {"max_percent": 96, "Match?": false}, {"max_percent": 24, "Match?": false}, {"max_percent": 8, "Match?": false}, {"max_percent": 93, "Match?": true}, {"max_percent": 97, "Match?": false}, {"max_percent": 97, "Match?": true}, {"max_percent": 100, "Match?": false}, {"max_percent": 100, "Match?": false}, {"max_percent": 2, "Match?": false}, {"max_percent": 2, "Match?": false}, {"max_percent": 90, "Match?": true}, {"max_percent": 89, "Match?": true}, {"max_percent": 0, "Match?": false}, {"max_percent": 0, "Match?": true}, {"max_percent": 100, "Match?": true}, {"max_percent": 100, "Match?": true}, {"max_percent": 97, "Match?": true}, {"max_percent": 100, "Match?": true}, {"max_percent": 99, "Match?": false}, {"max_percent": 99, "Match?": true}, {"max_percent": 60, "Match?": true}, {"max_percent": 29, "Match?": true}, {"max_percent": 88, "Match?": true}, {"max_percent": 100, "Match?": true}, {"max_percent": 96, "Match?": true}, {"max_percent": 60, "Match?": true}, {"max_percent": 84, "Match?": true}, {"max_percent": 100, "Match?": true}, {"max_percent": 97, "Match?": false}, {"max_percent": 5, "Match?": false}, {"max_percent": 22, "Match?": false}, {"max_percent": 96, "Match?": true}, {"max_percent": 39, "Match?": false}, {"max_percent": 100, "Match?": true}, {"max_percent": 22, "Match?": false}, {"max_percent": 85, "Match?": false}, {"max_percent": 99, "Match?": true}, {"max_percent": 100, "Match?": true}, {"max_percent": 56, "Match?": false}, {"max_percent": 97, "Match?": true}, {"max_percent": 52, "Match?": true}, {"max_percent": 100, "Match?": true}, {"max_percent": 44, "Match?": false}, {"max_percent": 99, "Match?": true}, {"max_percent": 88, "Match?": true}, {"max_percent": 93, "Match?": false}, {"max_percent": 91, "Match?": true}, {"max_percent": 25, "Match?": true}, {"max_percent": 100, "Match?": true}, {"max_percent": 100, "Match?": true}, {"max_percent": 100, "Match?": true}, {"max_percent": 100, "Match?": true}, {"max_percent": 0, "Match?": true}, {"max_percent": 97, "Match?": false}, {"max_percent": 0, "Match?": true}, {"max_percent": 96, "Match?": true}, {"max_percent": 99, "Match?": true}, {"max_percent": 1, "Match?": false}, {"max_percent": 1, "Match?": true}, {"max_percent": 100, "Match?": true}, {"max_percent": 83, "Match?": false}, {"max_percent": 98, "Match?": true}, {"max_percent": 99, "Match?": true}, {"max_percent": 99, "Match?": true}, {"max_percent": 94, "Match?": true}, {"max_percent": 96, "Match?": true}, {"max_percent": 0, "Match?": false}, {"max_percent": 87, "Match?": false}, {"max_percent": 83, "Match?": true}, {"max_percent": 80, "Match?": true}, {"max_percent": 84, "Match?": true}, {"max_percent": 95, "Match?": true}, {"max_percent": 99, "Match?": true}, {"max_percent": 78, "Match?": true}, {"max_percent": 45, "Match?": true}, {"max_percent": 96, "Match?": true}, {"max_percent": 79, "Match?": false}, {"max_percent": 86, "Match?": true}, {"max_percent": 21, "Match?": false}, {"max_percent": 99, "Match?": true}, {"max_percent": 53, "Match?": false}, {"max_percent": 3, "Match?": true}, {"max_percent": 95, "Match?": true}, {"max_percent": 79, "Match?": false}, {"max_percent": 99, "Match?": false}, {"max_percent": 99, "Match?": true}, {"max_percent": 1, "Match?": true}, {"max_percent": 60, "Match?": false}, {"max_percent": 1, "Match?": false}, {"max_percent": 82, "Match?": true}, {"max_percent": 73, "Match?": true}, {"max_percent": 95, "Match?": true}, {"max_percent": 75, "Match?": true}, {"max_percent": 95, "Match?": true}, {"max_percent": 97, "Match?": false}, {"max_percent": 99, "Match?": false}, {"max_percent": 100, "Match?": true}, {"max_percent": 86, "Match?": true}, {"max_percent": 5, "Match?": true}, {"max_percent": 100, "Match?": true}, {"max_percent": 98, "Match?": true}, {"max_percent": 63, "Match?": false}, {"max_percent": 74, "Match?": false}, {"max_percent": 98, "Match?": true}, {"max_percent": 98, "Match?": true}, {"max_percent": 100, "Match?": true}, {"max_percent": 38, "Match?": false}, {"max_percent": 11, "Match?": false}, {"max_percent": 1, "Match?": false}, {"max_percent": 98, "Match?": false}, {"max_percent": 50, "Match?": false}, {"max_percent": 99, "Match?": true}, {"max_percent": 0, "Match?": false}, {"max_percent": 98, "Match?": true}, {"max_percent": 97, "Match?": true}, {"max_percent": 95, "Match?": true}, {"max_percent": 91, "Match?": true}, {"max_percent": 34, "Match?": false}, {"max_percent": 20, "Match?": false}, {"max_percent": 1, "Match?": false}, {"max_percent": 96, "Match?": true}, {"max_percent": 98, "Match?": true}, {"max_percent": 35, "Match?": false}, {"max_percent": 99, "Match?": true}, {"max_percent": 98, "Match?": true}, {"max_percent": 60, "Match?": true}, {"max_percent": 100, "Match?": false}, {"max_percent": 100, "Match?": true}, {"max_percent": 98, "Match?": true}, {"max_percent": 98, "Match?": true}, {"max_percent": 89, "Match?": true}, {"max_percent": 70, "Match?": true}, {"max_percent": 69, "Match?": true}, {"max_percent": 95, "Match?": false}, {"max_percent": 95, "Match?": true}, {"max_percent": 2, "Match?": false}, {"max_percent": 91, "Match?": true}, {"max_percent": 72, "Match?": false}, {"max_percent": 100, "Match?": true}, {"max_percent": 99, "Match?": true}, {"max_percent": 93, "Match?": true}, {"max_percent": 100, "Match?": true}, {"max_percent": 91, "Match?": true}, {"max_percent": 88, "Match?": true}, {"max_percent": 0, "Match?": false}, {"max_percent": 100, "Match?": true}, {"max_percent": 100, "Match?": true}, {"max_percent": 80, "Match?": false}, {"max_percent": 3, "Match?": false}, {"max_percent": 92, "Match?": true}, {"max_percent": 92, "Match?": false}, {"max_percent": 88, "Match?": true}, {"max_percent": 100, "Match?": true}, {"max_percent": 97, "Match?": false}, {"max_percent": 79, "Match?": false}, {"max_percent": 61, "Match?": true}, {"max_percent": 14, "Match?": true}, {"max_percent": 100, "Match?": true}, {"max_percent": 37, "Match?": false}, {"max_percent": 99, "Match?": true}, {"max_percent": 21, "Match?": false}, {"max_percent": 85, "Match?": false}, {"max_percent": 98, "Match?": true}, {"max_percent": 83, "Match?": true}, {"max_percent": 100, "Match?": true}, {"max_percent": 82, "Match?": true}, {"max_percent": 89, "Match?": false}, {"max_percent": 36, "Match?": true}, {"max_percent": 99, "Match?": true}, {"max_percent": 86, "Match?": true}, {"max_percent": 20, "Match?": true}, {"max_percent": 97, "Match?": true}, {"max_percent": 83, "Match?": false}, {"max_percent": 93, "Match?": true}, {"max_percent": 100, "Match?": true}, {"max_percent": 8, "Match?": true}, {"max_percent": 96, "Match?": false}, {"max_percent": 98, "Match?": true}, {"max_percent": 1, "Match?": false}, {"max_percent": 96, "Match?": true}, {"max_percent": 99, "Match?": true}, {"max_percent": 5, "Match?": false}, {"max_percent": 36, "Match?": false}, {"max_percent": 3, "Match?": true}, {"max_percent": 99, "Match?": true}, {"max_percent": 90, "Match?": false}, {"max_percent": 98, "Match?": true}, {"max_percent": 100, "Match?": true}, {"max_percent": 79, "Match?": true}, {"max_percent": 98, "Match?": true}, {"max_percent": 100, "Match?": true}, {"max_percent": 96, "Match?": true}, {"max_percent": 92, "Match?": false}, {"max_percent": 27, "Match?": false}, {"max_percent": 94, "Match?": true}, {"max_percent": 97, "Match?": false}, {"max_percent": 15, "Match?": true}, {"max_percent": 94, "Match?": false}, {"max_percent": 100, "Match?": true}, {"max_percent": 60, "Match?": false}, {"max_percent": 100, "Match?": true}, {"max_percent": 0, "Match?": true}, {"max_percent": 22, "Match?": false}, {"max_percent": 97, "Match?": true}, {"max_percent": 23, "Match?": false}, {"max_percent": 93, "Match?": true}, {"max_percent": 92, "Match?": false}, {"max_percent": 97, "Match?": true}, {"max_percent": 100, "Match?": true}, {"max_percent": 100, "Match?": true}, {"max_percent": 90, "Match?": true}, {"max_percent": 96, "Match?": true}, {"max_percent": 87, "Match?": true}, {"max_percent": 66, "Match?": true}, {"max_percent": 96, "Match?": true}, {"max_percent": 99, "Match?": false}, {"max_percent": 20, "Match?": false}, {"max_percent": 96, "Match?": false}, {"max_percent": 89, "Match?": true}, {"max_percent": 91, "Match?": true}, {"max_percent": 98, "Match?": true}, {"max_percent": 0, "Match?": true}, {"max_percent": 96, "Match?": false}, {"max_percent": 70, "Match?": true}, {"max_percent": 68, "Match?": false}, {"max_percent": 100, "Match?": false}, {"max_percent": 98, "Match?": true}, {"max_percent": 20, "Match?": false}, {"max_percent": 82, "Match?": false}, {"max_percent": 95, "Match?": false}, {"max_percent": 99, "Match?": true}, {"max_percent": 88, "Match?": false}, {"max_percent": 94, "Match?": true}, {"max_percent": 99, "Match?": true}, {"max_percent": 95, "Match?": true}, {"max_percent": 81, "Match?": true}, {"max_percent": 98, "Match?": true}, {"max_percent": 92, "Match?": true}, {"max_percent": 98, "Match?": true}, {"max_percent": 0, "Match?": true}, {"max_percent": 100, "Match?": false}, {"max_percent": 92, "Match?": true}, {"max_percent": 90, "Match?": true}, {"max_percent": 100, "Match?": false}, {"max_percent": 90, "Match?": true}, {"max_percent": 100, "Match?": true}, {"max_percent": 44, "Match?": false}, {"max_percent": 2, "Match?": false}, {"max_percent": 93, "Match?": true}, {"max_percent": 88, "Match?": true}, {"max_percent": 96, "Match?": true}, {"max_percent": 83, "Match?": false}, {"max_percent": 49, "Match?": false}, {"max_percent": 23, "Match?": false}, {"max_percent": 63, "Match?": false}, {"max_percent": 65, "Match?": false}, {"max_percent": 93, "Match?": true}, {"max_percent": 26, "Match?": false}, {"max_percent": 100, "Match?": true}, {"max_percent": 99, "Match?": true}, {"max_percent": 99, "Match?": true}, {"max_percent": 99, "Match?": true}, {"max_percent": 100, "Match?": false}, {"max_percent": 100, "Match?": true}, {"max_percent": 100, "Match?": true}, {"max_percent": 99, "Match?": true}, {"max_percent": 95, "Match?": true}]